{"ticker": "SB1NO.OL", "navn": "SpareBank 1 S\u00f8r-Norge ASA", "sektor": "Financial Services", "bransje": "Banks - Regional", "pe_trailing": 12.536786, "pe_forward": 11.72262, "pb_ratio": 1.5506586, "ps_ratio": 5.810239, "peg_ratio": null, "profit_margin": 0.48901, "operating_margin": 0.6003, "roe": 0.12380999, "roa": 0.01349, "revenue_growth": 0.065, "earnings_growth": 0.166, "debt_to_equity": null, "current_ratio": null, "quick_ratio": null, "dividend_yield": 5.73, "payout_ratio": 0.50060004, "market_cap": 79536357376, "enterprise_value": 291608559616, "hentet": "2026-02-20T19:05:47.296821"}