{"ticker": "ATEA.OL", "navn": "ATEA", "sektor": "Technology", "bransje": "Information Technology Services", "pe_trailing": 18.59173, "pe_forward": 12.791111, "pb_ratio": 3.531115, "ps_ratio": 0.4294371, "peg_ratio": null, "profit_margin": 0.02349, "operating_margin": 0.04346, "roe": 0.19589001, "roa": 0.04078, "revenue_growth": 0.06, "earnings_growth": 0.305, "debt_to_equity": 48.183, "current_ratio": 0.937, "quick_ratio": 0.871, "dividend_yield": 4.84, "payout_ratio": 0.90559995, "market_cap": 16050640896, "enterprise_value": 16706757632, "hentet": "2026-02-24T11:39:42.828243"}