{"ticker": "ORK.OL", "navn": "ORKLA", "sektor": "Consumer Defensive", "bransje": "Packaged Foods", "pe_trailing": 20.47022, "pe_forward": 18.101404, "pb_ratio": 2.671959, "ps_ratio": 1.7916818, "peg_ratio": null, "profit_margin": 0.16036, "operating_margin": 0.10439, "roe": 0.13402, "roa": 0.052729998, "revenue_growth": -0.001, "earnings_growth": 0.39, "debt_to_equity": 32.105, "current_ratio": 1.426, "quick_ratio": 0.801, "dividend_yield": 3.07, "payout_ratio": 0.62700003, "market_cap": 128189456384, "enterprise_value": 147811762176, "hentet": "2026-02-24T11:26:51.889534"}